README.md
setup.cfg
setup.py
gitpullall/__init__.py
gitpullall/gitpullall.py
gitpullall.egg-info/PKG-INFO
gitpullall.egg-info/SOURCES.txt
gitpullall.egg-info/dependency_links.txt
gitpullall.egg-info/entry_points.txt
gitpullall.egg-info/top_level.txt