Metadata-Version: 1.0
Name: gitpullall
Version: 1.0.6
Summary: A Python module that calls "git pull" on all subfolders
Home-page: https://github.com/AlexFlipnote/gitpullall
Author: AlexFlipnote
Author-email: UNKNOWN
License: GNU v3
Platform: UNKNOWN
